{
  "name": "Ultimate Challenge",
  "background": "0x123456",
  "platformColor": "0xABCDEF",
  "platforms": [
    { "x": 0, "y": 0, "z": 0, "width": 5, "depth": 5, "height": 1, "isFirst": true },
    { "x": 10, "y": 2, "z": 5, "width": 4, "depth": 4, "height": 1 },
    { "x": 15, "y": 4, "z": 10, "width": 3, "depth": 3, "height": 1, "moveSpeed": 2, "moveAxis": "z", "moveRange": 3 },
    { "x": 20, "y": 6, "z": 15, "width": 2, "depth": 2, "height": 1 },
    { "x": 25, "y": 8, "z": 20, "width": 3, "depth": 3, "height": 1, "moveSpeed": 2, "moveAxis": "x", "moveRange": 4 },
    { "x": 30, "y": 10, "z": 25, "width": 4, "depth": 4, "height": 1 },
    { "x": 35, "y": 5, "z": 15, "width": 1, "depth": 4, "height": 8 },
    { "x": 40, "y": 12, "z": 30, "width": 3, "depth": 3, "height": 1 },
    { "x": 45, "y": 6, "z": 20, "width": 10, "depth": 1, "height": 10 },
    { "x": 50, "y": 14, "z": 35, "width": 4, "depth": 4, "height": 1, "moveSpeed": 3, "moveAxis": "y", "moveRange": 5 },
    { "x": 55, "y": 16, "z": 40, "width": 2, "depth": 2, "height": 1 },
    { "x": 60, "y": 18, "z": 45, "width": 3, "depth": 3, "height": 1, "moveSpeed": 2, "moveAxis": "z", "moveRange": 4 },
    { "x": 65, "y": 20, "z": 50, "width": 4, "depth": 4, "height": 1 },
    { "x": 70, "y": 22, "z": 55, "width": 2, "depth": 2, "height": 1, "moveSpeed": 3, "moveAxis": "x", "moveRange": 3 },
    { "x": 75, "y": 24, "z": 60, "width": 3, "depth": 3, "height": 1 },
    { "x": 80, "y": 26, "z": 65, "width": 4, "depth": 4, "height": 1, "moveSpeed": 2, "moveAxis": "y", "moveRange": 5 },
    { "x": 85, "y": 28, "z": 70, "width": 3, "depth": 3, "height": 1 },
    { "x": 90, "y": 30, "z": 75, "width": 2, "depth": 2, "height": 1, "moveSpeed": 3, "moveAxis": "z", "moveRange": 4 },
    { "x": 95, "y": 32, "z": 80, "width": 4, "depth": 4, "height": 1 },
    { "x": 100, "y": 34, "z": 85, "width": 3, "depth": 3, "height": 1, "moveSpeed": 2, "moveAxis": "x", "moveRange": 3 },
    { "x": 105, "y": 36, "z": 90, "width": 2, "depth": 2, "height": 1 },
    { "x": 110, "y": 38, "z": 95, "width": 3, "depth": 3, "height": 1, "moveSpeed": 3, "moveAxis": "y", "moveRange": 5 },
    { "x": 115, "y": 40, "z": 100, "width": 4, "depth": 4, "height": 1 },
    { "x": 120, "y": 42, "z": 105, "width": 2, "depth": 2, "height": 1, "moveSpeed": 2, "moveAxis": "z", "moveRange": 4 },
    { "x": 125, "y": 44, "z": 110, "width": 3, "depth": 3, "height": 1 },
    { "x": 130, "y": 46, "z": 115, "width": 4, "depth": 4, "height": 1, "moveSpeed": 3, "moveAxis": "x", "moveRange": 3 },
    { "x": 135, "y": 48, "z": 120, "width": 2, "depth": 2, "height": 1 },
    { "x": 140, "y": 50, "z": 125, "width": 3, "depth": 3, "height": 1, "moveSpeed": 2, "moveAxis": "y", "moveRange": 5 },
    { "x": 145, "y": 52, "z": 130, "width": 4, "depth": 4, "height": 1 },
    { "x": 150, "y": 54, "z": 135, "width": 3, "depth": 3, "height": 1, "isFinal": true }
  ]
}
